scrapy_promise/__init__.py
scrapy_promise/_version.py
scrapy_promise/promise.py
scrapy_promise-0.0.6.dist-info/LICENSE
scrapy_promise-0.0.6.dist-info/METADATA
scrapy_promise-0.0.6.dist-info/WHEEL
scrapy_promise-0.0.6.dist-info/top_level.txt
scrapy_promise-0.0.6.dist-info/RECORD
