Metadata-Version: 2.1
Name: scrapy-promise
Version: 0.0.6
Summary: Promise-style workflow for Scrapy
Home-page: https://github.com/monotony113/scrapy-promise
Author: Tony Wu
Author-email: tony(dot)wu(at)nyu(dot)edu@inval.id
License: MIT
Keywords: promise scrapy
Platform: UNKNOWN
Classifier: Development Status :: 3 - Alpha
Classifier: Intended Audience :: Developers
Classifier: Intended Audience :: End Users/Desktop
Classifier: License :: OSI Approved :: MIT License
Classifier: Programming Language :: Python :: 3 :: Only
Classifier: Programming Language :: Python :: 3.6
Classifier: Programming Language :: Python :: 3.7
Classifier: Programming Language :: Python :: 3.8
Classifier: Topic :: Software Development :: Libraries
Classifier: Framework :: Scrapy
Requires-Python: >=3.6
Requires-Dist: notcallback (>=0.0.8)
